mujoco_usd_converter/__init__.py
mujoco_usd_converter/__main__.py
mujoco_usd_converter/_version.py
mujoco_usd_converter/_impl/_flatten.py
mujoco_usd_converter/_impl/actuator.py
mujoco_usd_converter/_impl/body.py
mujoco_usd_converter/_impl/cli.py
mujoco_usd_converter/_impl/convert.py
mujoco_usd_converter/_impl/data.py
mujoco_usd_converter/_impl/geom.py
mujoco_usd_converter/_impl/joint.py
mujoco_usd_converter/_impl/material.py
mujoco_usd_converter/_impl/mesh.py
mujoco_usd_converter/_impl/numpy.py
mujoco_usd_converter/_impl/scene.py
mujoco_usd_converter/_impl/utils.py
mujoco_usd_converter/plugins/plugInfo.json
mujoco_usd_converter/plugins/mjcPhysics/resources/generatedSchema.usda
mujoco_usd_converter/plugins/mjcPhysics/resources/plugInfo.json
mujoco_usd_converter-0.1.0a5.dist-info/METADATA
mujoco_usd_converter-0.1.0a5.dist-info/WHEEL
mujoco_usd_converter-0.1.0a5.dist-info/entry_points.txt
mujoco_usd_converter-0.1.0a5.dist-info/licenses/LICENSE.md
mujoco_usd_converter-0.1.0a5.dist-info/RECORD
