Metadata-Version: 2.4
Name: mujoco-usd-converter
Version: 0.1.0a5
Summary: A MuJoCo to OpenUSD Data Converter
Project-URL: Documentation, https://github.com/newton-physics/mujoco-usd-converter/#readme
Project-URL: Repository, https://github.com/newton-physics/mujoco-usd-converter
Project-URL: Changelog, https://github.com/newton-physics/mujoco-usd-converter/blob/main/CHANGELOG.md
Author: Newton Developers
License: Apache-2.0
License-File: LICENSE.md
Requires-Python: <3.13,>=3.10
Requires-Dist: mujoco==3.4.0
Requires-Dist: numpy-stl>=3.2
Requires-Dist: tinyobjloader>=2.0.0rc13
Requires-Dist: usd-exchange>=2.2.0
